tributors/__init__.py
tributors/logger.py
tributors/version.py
tributors/client/__init__.py
tributors/client/init.py
tributors/client/lookup.py
tributors/client/update.py
tributors/client/utils.py
tributors/main/__init__.py
tributors/main/github.py
tributors/main/orcid.py
tributors/main/parsers/__init__.py
tributors/main/parsers/allcontrib.py
tributors/main/parsers/base.py
tributors/main/parsers/codemeta.py
tributors/main/parsers/mailmap.py
tributors/main/parsers/zenodo.py
tributors/utils/command.py
tributors/utils/file.py
tributors/utils/prompt.py
tributors-0.1.1.dist-info/LICENSE
tributors-0.1.1.dist-info/METADATA
tributors-0.1.1.dist-info/WHEEL
tributors-0.1.1.dist-info/entry_points.txt
tributors-0.1.1.dist-info/top_level.txt
tributors-0.1.1.dist-info/RECORD
