Metadata-Version: 2.1
Name: tributors
Version: 0.1.1
Summary: give tribute to your repository contributors.
Home-page: http://www.github.com/con/tributors
Author: Vanessa Sochat
Author-email: vsochat@stanford.edu
Maintainer: Vanessa Sochat
Maintainer-email: vsochat@stanford.edu
License: LICENSE
Keywords: contributions,tributes
Classifier: Intended Audience :: Science/Research
Classifier: Intended Audience :: Developers
Classifier: License :: OSI Approved :: Mozilla Public License 2.0 (MPL 2.0)
Classifier: Topic :: Software Development
Classifier: Topic :: Scientific/Engineering
Classifier: Natural Language :: English
Classifier: Operating System :: Unix
Classifier: Programming Language :: Python :: 3
Classifier: Programming Language :: Python :: 3.5
Classifier: Programming Language :: Python :: 3.6
Classifier: Programming Language :: Python :: 3.7
Classifier: Programming Language :: Python :: 3.8
License-File: LICENSE
Requires-Dist: requests (>=2.23.0)
Provides-Extra: all
Requires-Dist: requests (>=2.23.0) ; extra == 'all'
Requires-Dist: codemetapy (>=0.3.2) ; extra == 'all'
Provides-Extra: codemeta
Requires-Dist: codemetapy (>=0.3.2) ; extra == 'codemeta'
